 {
  "titleNameMap": {
    "educationList": "教育背景",
    "workExpList": "工作经历",
    "projectList": "项目经验",
    "skillList": "个人技能",
    "awardList": "更多信息",
    "workList": "个人作品",
    "aboutme": "个人评价"
  },
  "avatar": {
    "src": "https://pic.imgdb.cn/item/65850325c458853aef8d8938.jpg",
    "hidden": false
  },
  "profile": {
    "name": "陈雪娇",
    "email": "1286707605@qq.com",
    "mobile": "18855154498",
    "github": "",
    "zhihu": "",
    "workExpYear": ""
  },
  "educationList": [
    {
      "edu_time": [
        "2018.09.01",
        "2022.06.30"
      ],
      "school": "安徽工业大学",
      "major": "工业设计",
      "academic_degree": "本科"
    }
  ],
  "awardList": [
    {
      "award_info": "安徽省工业设计大赛专项优秀奖",
      "award_time": "2019.10"
    },
    {
      "award_info": "安徽工业大学校级优秀社会工作者",
      "award_time": "2020.07-2021.08"
    },
    {
      "award_info": "安徽工业大学校级三等奖学金",
      "award_time": "2020-2021学年"
    },
    {
      "award_info": "安徽工业大学校级特等奖学金",
      "award_time": "2021-2022学年"
    },
    {
      "award_info": "CET6",
      "award_time": "2019.12"
    },
    {
      "award_info": "安徽省第九届工业设计大赛二等奖",
      "award_time": "2022.10"
    },
    {
      "award_info": "第六届全国大学生工业设计大赛（安徽赛区）一等奖",
      "award_time": "2022.10"
    },
    {
      "award_info": "外观专利：摆件（摇摆艺术装置）（ZL 2023 3 0046447.2）",
      "award_time": "2023.06"
    },
    {
      "award_info": "外观专利：音箱（火星机械木偶）（ZL 2023 3 0046455.7）",
      "award_time": "2023.06"
    },
    {
      "award_info": "实用新型专利：一种椭圆形舞台展览互动装置（ZL 2023 2 0476043.1）",
      "award_time": "2023.10"
    },
    {
      "award_info": "实用新型专利：一种基于激光雷达的声音交互装置（ZL 2023 2 0430217.0）",
      "award_time": "2023.11"
    },
    {
      "award_info": "实用新型专利：一种基于毫米雷达的感应互动式泡泡制造机（ZL 2023 2 0475047.X）",
      "award_time": "2023.11"
    }
  ],
  "workExpList": [
    {
      "company_name": "北京吉星宝科技有限公司",
      "department_name": "研发部",
      "work_time": [
        "2022.08",
        "2023.08"
      ],
    "work_desc": "1.负责两款猫型音箱设计与开发\n2.负责”2022年武汉市双年展“——三件大型交互类艺术装置设计与开发\n3.两种新型互动雾化式多味联动香薰机的设计与开发"    },
    {
      "company_name": "北京星之桥文化科技有限公司",
      "department_name": "设计部",
      "work_time": [
        "2023.08",
        "至今"
      ],
      "work_desc": "1.北京市昌平区知蜂堂蜜蜂博物馆陈列展项结构设计与生产制作\n2.新西兰WETA DIGITAL卡塔尔阿布扎比古生物历史博物馆大型古生物雕塑结构设计与制作\r\n3.电影首映礼展会道具制作"    }
  ],
  "skillList": [],
  "projectList": [
    {
      "project_name": "两款猫型蓝牙HIFI音箱量产计划",
      "project_role": "结构工程师",
      "project_time": "2022.08 - 2023.8",
      "project_desc": "面向开放式轻奢场所设计的高装饰性蓝牙交互音箱",
      "project_content": "1.使用SW、FUSION对音箱的整体结构设计，根据SPCAD分析计算测试改良装置气腔容积\n2.导声箱体新型改良设计及量产模具制作\n3.安排制作工艺和流程及标准件选型，对接生产部门制作打样\n4.优化设计，评估产品可行性，总结设计图纸，BOM表格处理"
    },
    {
      "project_name": "面向武汉2022年度双年展会大型艺术装置交互设计",
      "project_role": "结构工程师",
      "project_time": "2022.9 - 2022.12",
      "project_desc": "基于毫米波雷达的感应式互动泡泡制造艺术装置；基于激光雷达的声音交互装置；基于红外传感器的舞台展览互动装置",
      "project_content": "\n1. 三件大型艺术装置内部框架整体结构设计，进行有限元分析评估前期安全性优化设计方案\n2.配合电控部门选型和前期实验打样，完善功能和达到预期效果\n3. 管控后期生产制作及材料工艺制作，安排实际落地及工作验收"    },
    {
      "project_name": "面向商业、个人空间的两种新型互动雾化式多味联动香薰机的设计与开发",
      "project_role": "结构工程师",
      "project_time": "2023.3 - 2023.8",
      "project_desc": "基于",
      "project_content": "负责项目整体解决方案的设计和开发\n1.负责手机客户端的设计和开发\n2.负责手机探测后端的设计和开发\n3.负责手机探测前端的设计和开发"
    },
    {
      "project_name": "OpenStack国产化",
      "project_role": "项目负责人",
      "project_time": "2022.11 - 至今",
      "project_desc": "现网都是基于Centos搭建的OpenStack-Pike版，国产化原因需要升级到BC欧拉操作系统",
      "project_content": "1.将Pike版OpenStack由Python2.7升级到Python3.6\n2.在BC欧拉中安装OpenStack-Pike并形成完整的部署方案交付到运维侧进行批量部署测试" 
    },
    {
      "project_name": "云迁移调度平台",
      "project_role": "技术负责人",
      "project_time": "2023.6 - 2023.12",
      "project_desc": "给用户提供上云方案，同POD、跨POD迁移，KVM2KVM迁移，VMWare2KVM迁移，IRONIC2KVM迁移，UEFI转LEGACY启动",
      "project_content": "负责迁移核心服务框架设计和开发，实现KVM2KVM迁移，VMWare2KVM迁移，IRONIC2KVM迁移，UEFI转LEGACY启动，支持增量迁移，可以通过SSH、镜像等多种方式迁移OS" 
    },
    {
      "project_name": "SD-WAN",
      "project_role": "项目负责人",
      "project_time": "2023.12 - 至今",
      "project_desc": "基于软件定义网络(SDN)的思想，设计和实现的一种新型网络技术。解决现代大型企业在全球不同区域的网络连通性，提高网络管理效率，并降低网络管理成本。",
      "project_content": "1.在企业入口点通过CPE设备连接到骨干网，在广域网的基础上构建私有隧道\n2.通过SDWAN控制器来实现路由的选择以及流量监控等功能" 
    }
  ],
  "workList": [],
  "aboutme": {
    "aboutme_desc": "两年云计算IAAS层研发经验\n1. 项目管理: 具有独立跟进和推动项目进度经验，把控研发测试交付进展。\n2.云计算运维:能够快速定位OpenStack问题点并进行分析解决\n3.云计算研发:针对OpenStack的研发能力，具有独立开发和测试经验"
  },
  "theme": {
    "color": "#2f5785",
    "tagColor": "#8bc34a"
  }
}
